tattletail/__init__.py
tattletail/analyzer.py
tattletail/context.py
tattletail/models.py
tattletail/parser.py
tattletail-0.1.0.dist-info/METADATA
tattletail-0.1.0.dist-info/WHEEL
tattletail-0.1.0.dist-info/licenses/LICENSE
tattletail-0.1.0.dist-info/RECORD
