Metadata-Version: 2.4
Name: tattletail
Version: 0.1.0
Summary: Python tracebacks like structured, analyzable data with rich insights.
Project-URL: Homepage, https://github.com/ericmiguel/tattletail
Project-URL: Documentation, https://github.com/ericmiguel/tattletail#readme
Project-URL: Repository, https://github.com/ericmiguel/tattletail.git
Project-URL: Bug Tracker, https://github.com/ericmiguel/tattletail/issues
Project-URL: Changelog, https://github.com/ericmiguel/tattletail/blob/main/CHANGELOG.md
Author-email: Eric Miguel <ericmiguel@example.com>
License: AGPL-3.0-or-later
License-File: LICENSE
Keywords: analysis,debugging,error,python,traceback
Classifier: Development Status :: 4 - Beta
Classifier: Intended Audience :: Developers
Classifier: License :: OSI Approved :: GNU Affero General Public License v3
Classifier: Programming Language :: Python
Classifier: Programming Language :: Python :: 3
Classifier: Programming Language :: Python :: 3.12
Classifier: Programming Language :: Python :: Implementation :: CPython
Classifier: Topic :: Software Development :: Debuggers
Requires-Python: >=3.12
